scDeepJointClust/Celltype.py
scDeepJointClust/Configurations.py
scDeepJointClust/Utils.py
scDeepJointClust/__init__.py
scDeepJointClust/example.py
scDeepJointClust/.ipynb_checkpoints/__init__-checkpoint.py
scDeepJointClust/.ipynb_checkpoints/example-checkpoint.py
scdeepjointclust-0.0.1.dist-info/METADATA
scdeepjointclust-0.0.1.dist-info/WHEEL
scdeepjointclust-0.0.1.dist-info/licenses/LICENSE.txt
scdeepjointclust-0.0.1.dist-info/RECORD
